ppjson/__init__.py
ppjson/ppjson.py
ppjson-0.0.1.dist-info/METADATA
ppjson-0.0.1.dist-info/RECORD
ppjson-0.0.1.dist-info/WHEEL
ppjson-0.0.1.dist-info/top_level.txt
