Metadata-Version: 2.1
Name: ppjson
Version: 0.0.1
Summary: another json str loads
Home-page: https://github.com/jiamo/ppjson
Author: jiamo
Author-email: life.130815@gmail.com
License: MIT
Keywords: ppjson
Platform: UNKNOWN
Classifier: Development Status :: 2 - Pre-Alpha
Classifier: Intended Audience :: Developers
Classifier: Natural Language :: English
Classifier: Programming Language :: Python :: 3.6
Requires-Dist: sly
